{
   "component" : "error_detector",
   "source_file" : "error_detector.json",
   "steps" : [
      {
         "category" : "infrastructure",
         "executable" : "/bin/env mkdir",
         "idx" : 0,
         "name" : "create output directory",
         "run_type" : "RunUnixCommand"
      },
      {
         "category" : "infrastructure",
         "executable" : "/bin/env mkdir",
         "idx" : 1,
         "name" : "create temp directory",
         "run_type" : "RunUnixCommand"
      },
      {
         "category" : "tool_execution",
         "executable" : "{{BIN_DIR}}/error_detector",
         "idx" : 2,
         "name" : "error detector"
      }
   ]
}
