{
   "component" : "tmhmm",
   "source_file" : "tmhmm.i1.json",
   "steps" : [
      {
         "category" : "tool_execution",
         "executable" : "{{TMHMM_EXEC}}",
         "idx" : 0,
         "name" : "tmhmm"
      },
      {
         "category" : "converter",
         "executable" : "{{BIN_DIR}}/tmhmm2bsml",
         "idx" : 1,
         "name" : "tmhmm2bsml"
      },
      {
         "category" : "provenance",
         "executable" : "{{BIN_DIR}}/analysis2bsml",
         "idx" : 2,
         "name" : "store config params"
      },
      {
         "category" : "validation",
         "executable" : "{{BIN_DIR}}/dtdValid.pl",
         "idx" : 3,
         "name" : "dtd validation"
      }
   ]
}
